{
  "id": "",
  "name": "",
  "font_family": "iconfont",
  "css_prefix_text": "icon-",
  "description": "",
  "glyphs": [
    {
      "icon_id": "880160",
      "name": "举报",
      "font_class": "jubao",
      "unicode": "e601",
      "unicode_decimal": 58881
    },
    {
      "icon_id": "2678607",
      "name": "回到顶部",
      "font_class": "huidaodingbu",
      "unicode": "e64d",
      "unicode_decimal": 58957
    },
    {
      "icon_id": "12620012",
      "name": "意见反馈",
      "font_class": "icon_A",
      "unicode": "e6a0",
      "unicode_decimal": 59040
    },
    {
      "icon_id": "23641480",
      "name": "客服",
      "font_class": "kefu",
      "unicode": "e629",
      "unicode_decimal": 58921
    }
  ]
}
